twintel/__init__.py
twintel/_methods/__init__.py
twintel/_methods/flatfile.py
twintel/_methods/search.py
twintel/_methods/stream.py
twintel/_methods/timeline.py
twintel/_processing/__init__.py
twintel/_processing/data_frame.py
twintel/_processing/data_prep.py
twintel/_processing/semantics.py
twintel/_resources/__init__.py
twintel/_resources/keys.py
twintel/_resources/stopword.py
twintel-1.5.2.dist-info/LICENSE
twintel-1.5.2.dist-info/METADATA
twintel-1.5.2.dist-info/WHEEL
twintel-1.5.2.dist-info/top_level.txt
twintel-1.5.2.dist-info/RECORD
