Metadata-Version: 2.1
Name: twintel
Version: 1.5.2
Summary: Twitter data for signals intelligence
Home-page: http://github.com/mikkokotila
Author: Mikko Kotila
Author-email: mailme@mikkokotila.com
Maintainer: Mikko Kotila
Maintainer-email: mailme@mikkokotila.com
License: MIT
Download-URL: https://github.com/mikkokotila/twintel
Platform: UNKNOWN
Classifier: Intended Audience :: Science/Research
Classifier: Programming Language :: Python :: 3.7
Classifier: Programming Language :: Python :: 3.8
Classifier: Operating System :: POSIX
Classifier: Operating System :: Unix
Classifier: Operating System :: MacOS
Requires-Dist: pandas
Requires-Dist: nltk
Requires-Dist: tweepy
Requires-Dist: twython
Requires-Dist: aiohttp-socks
